lutz-0.1.9.dist-info/METADATA
lutz-0.1.9.dist-info/WHEEL
lutz-0.1.9.dist-info/license_files/LICENSE
lutz/util.py
lutz/rust.py
lutz/__init__.py
lutz/_lib.cpython-312-aarch64-linux-gnu.so
lutz-0.1.9.dist-info/RECORD
