Metadata-Version: 2.1
Name: lutz
Version: 0.1.9
Requires-Dist: fortune-python
License-File: LICENSE
Summary: Python package setup for adding some additional rust functions
Requires-Python: >=3.9
